{
"CPU": 8.010814,
"Starttime": 1720639414,
"Epoch": 1720639414,
"Version": "09",
"MaxNodesPerDevice": 1,
"Connections": 0,
"Nodes": 0,
"NodesFree": 0,
"NodesWorking": 0,
"Validators": 0,
"ValidatorsFree": 0,
"ValidatorsWorking": 0,
"MaxNodes": 1024,
"TV": 0.001000,
"UsersCount": 4,
"TotalBalance": 150021,
"TaskTimeout": 120000 ,
"Throttled": 0,
"TasksCount": 1,
"TasksNew": 1,
"TasksRunning": 0,
"TasksFailed": 0,
"TasksCompleted": 0,
"TasksValidated": 0,
"TotalTasks": 1193209,
"TelemetryRetention": 86400,
"TelemetryCount": 8,
"TelemetryChunks": 16,
"TelemetryChunksLost": 9,
"TelemetrySize": 60781,
"Utilization": 0.000000,
"Users":[
{
"Username": "FuchsiaChocolateChuanjiesaurus",
"Rank": 46,
"Created": 1691434053,
"LastSeen": 1720633731,
"Balance": 60416,
"Good": 100,
"Bad": 0,
"UPF": 100,
"Totals": 327159,
"Submits": 184033,
"TelemetryCount": 1,
"TelemetryMax": 6,
"TelemetrySize": 10000,
"UPFDetais":"1111111111111111111111111111111111111111111111111111111111111111111111111111111111111111111111111111","Retention": 86400,
"Validator": 0,
"Nodes": 0,
"Awards":[
{
"Category": 0,
"Medal": 3
},
{
"Category": 1,
"Medal": 3
},
{
"Category": 2,
"Medal": 0
},
{
"Category": 3,
"Medal": 2
}
],
"Telemetry":[
{
"Created": 1720633681,
"Modified": 1720633681,
"Size": "134",
"Name": "FuchsiaChocolateChuanjiesaurusPOCNET"
}
],
"NodesList":[
]
},
{
"Username": "GRIDSHELLCoreValidators1",
"Rank": 10,
"Created": 1664609779,
"LastSeen": 1720633732,
"Balance": 1,
"Good": 88,
"Bad": 12,
"UPF": 88,
"Totals": 33,
"Submits": 126057,
"TelemetryCount": 4,
"TelemetryMax": 10,
"TelemetrySize": 100000,
"UPFDetais":"0000000000001111111111111111111111111111111111111111111111111111111111111111111111111111111111111111","Retention": 172800,
"Validator": 1,
"Nodes": 0,
"Awards":[
{
"Category": 0,
"Medal": 3
},
{
"Category": 1,
"Medal": 1
},
{
"Category": 2,
"Medal": 0
},
{
"Category": 3,
"Medal": 0
}
],
"Telemetry":[
{
"Created": 1720633402,
"Modified": 1720633402,
"Size": "9089",
"Name": "GRIDSHELLCoreValidators1CURRENT"
},
{
"Created": 1720562977,
"Modified": 1720639414,
"Size": "12201",
"Name": "GRIDSHELLCoreValidators1STAT2024710"
},
{
"Created": 1720476433,
"Modified": 1720562376,
"Size": "14664",
"Name": "GRIDSHELLCoreValidators1STAT202479"
},
{
"Created": 1720633402,
"Modified": 1720633402,
"Size": "12110",
"Name": "GRIDSHELLCoreValidators1TASKS"
}
],
"NodesList":[
]
},
{
"Username": "trialestesalamosaurustianzhenosaurus",
"Rank": 0,
"Created": 1708705684,
"LastSeen": 1720633732,
"Balance": 13930,
"Good": 100,
"Bad": 0,
"UPF": 100,
"Totals": 13615,
"Submits": 3128,
"TelemetryCount": 0,
"TelemetryMax": 5,
"TelemetrySize": 10000,
"UPFDetais":"1111111111111111111111111111111111111111111111111111111111111111111111111111111111111111111111111111","Retention": 86400,
"Validator": 0,
"Nodes": 0,
"Awards":[
{
"Category": 0,
"Medal": 1
},
{
"Category": 1,
"Medal": 2
},
{
"Category": 2,
"Medal": 0
},
{
"Category": 3,
"Medal": 1
}
],
"Telemetry":[
],
"NodesList":[
]
},
{
"Username": "JadeChartreuseDromiceiomimus",
"Rank": 100,
"Created": 1668685680,
"LastSeen": 1720633730,
"Balance": 75674,
"Good": 100,
"Bad": 0,
"UPF": 100,
"Totals": 700498,
"Submits": 369863,
"TelemetryCount": 3,
"TelemetryMax": 1001,
"TelemetrySize": 1500000,
"UPFDetais":"1111111111111111111111111111111111111111111111111111111111111111111111111111111111111111111111111111","Retention": 604800,
"Validator": 0,
"Nodes": 0,
"Awards":[
{
"Category": 0,
"Medal": 3
},
{
"Category": 1,
"Medal": 3
},
{
"Category": 2,
"Medal": 0
},
{
"Category": 3,
"Medal": 2
}
],
"Telemetry":[
{
"Created": 1720085625,
"Modified": 1720127303,
"Size": "5187",
"Name": "JadeChartreuseDromiceiomimusBUOY202474"
},
{
"Created": 1720174181,
"Modified": 1720191707,
"Size": "2276",
"Name": "JadeChartreuseDromiceiomimusBUOY202475"
},
{
"Created": 1720101920,
"Modified": 1720101928,
"Size": "5120",
"Name": "JadeChartreuseDromiceiomimusTUFFODB"
}
],
"NodesList":[
]
}
]
}