{
"CPU": 2.428941,
"Starttime": 1720772720,
"Epoch": 1722263200,
"Version": "09",
"MaxNodesPerDevice": 1,
"Connections": 28,
"Nodes": 28,
"NodesFree": 26,
"NodesWorking": 0,
"Validators": 2,
"ValidatorsFree": 2,
"ValidatorsWorking": 0,
"MaxNodes": 1024,
"TV": 0.000048,
"UsersCount": 4,
"TotalBalance": 152716,
"TaskTimeout": 120000 ,
"Throttled": 535,
"TasksCount": 5,
"TasksNew": 1,
"TasksRunning": 0,
"TasksFailed": 0,
"TasksCompleted": 0,
"TasksValidated": 4,
"TotalTasks": 1211768,
"TelemetryRetention": 86400,
"TelemetryCount": 6,
"TelemetryChunks": 10,
"TelemetryChunksLost": 1,
"TelemetrySize": 36351,
"Utilization": 0.000000,
"Users":[
{
"Username": "FuchsiaChocolateChuanjiesaurus",
"Rank": 49,
"Created": 1691434053,
"LastSeen": 1722263199,
"Balance": 59172,
"Good": 100,
"Bad": 0,
"UPF": 100,
"Totals": 340211,
"Submits": 197685,
"TelemetryCount": 1,
"TelemetryMax": 6,
"TelemetrySize": 10000,
"UPFDetais":"1111111111111111111111111111111111111111111111111111111111111111111111111111111111111111111111111111","Retention": 86400,
"Validator": 0,
"Nodes": 18,
"Awards":[
{
"Category": 0,
"Medal": 3
},
{
"Category": 1,
"Medal": 3
},
{
"Category": 2,
"Medal": 2
},
{
"Category": 3,
"Medal": 2
}
],
"Telemetry":[
{
"Created": 1722263041,
"Modified": 1722263041,
"Size": "134",
"Name": "FuchsiaChocolateChuanjiesaurusPOCNET"
}
],
"NodesList":[
{
"Group": 3,
"Version": "09",
"Task": 0,
"Validator": 0,
"Executor": 1,
"TelemetryChunks": 0,
"ExecsCount": 22,
"Availability": 75.047454,
"Ident": "788b0ddf6628"
},
{
"Group": 3,
"Version": "09",
"Task": 0,
"Validator": 0,
"Executor": 1,
"TelemetryChunks": 1,
"ExecsCount": 22,
"Availability": 75.047454,
"Ident": "156523da0b4a"
},
{
"Group": 3,
"Version": "09",
"Task": 0,
"Validator": 0,
"Executor": 1,
"TelemetryChunks": 0,
"ExecsCount": 26,
"Availability": 75.047454,
"Ident": "224e35d8c645"
},
{
"Group": 3,
"Version": "09",
"Task": 0,
"Validator": 0,
"Executor": 1,
"TelemetryChunks": 0,
"ExecsCount": 21,
"Availability": 75.047454,
"Ident": "734a368181a4"
},
{
"Group": 3,
"Version": "09",
"Task": 0,
"Validator": 0,
"Executor": 1,
"TelemetryChunks": 0,
"ExecsCount": 25,
"Availability": 75.049769,
"Ident": "efcdaaa2e73d"
},
{
"Group": 3,
"Version": "09",
"Task": 0,
"Validator": 0,
"Executor": 1,
"TelemetryChunks": 0,
"ExecsCount": 19,
"Availability": 75.047454,
"Ident": "ff2f18073865"
},
{
"Group": 3,
"Version": "09",
"Task": 0,
"Validator": 0,
"Executor": 1,
"TelemetryChunks": 1,
"ExecsCount": 22,
"Availability": 75.047454,
"Ident": "a144ae321d4f"
},
{
"Group": 3,
"Version": "09",
"Task": 0,
"Validator": 0,
"Executor": 1,
"TelemetryChunks": 0,
"ExecsCount": 21,
"Availability": 75.046296,
"Ident": "8d7bb5cc776c"
},
{
"Group": 3,
"Version": "09",
"Task": 0,
"Validator": 0,
"Executor": 1,
"TelemetryChunks": 0,
"ExecsCount": 16,
"Availability": 75.046296,
"Ident": "0a4d9c15a412"
},
{
"Group": 3,
"Version": "09",
"Task": 0,
"Validator": 0,
"Executor": 1,
"TelemetryChunks": 0,
"ExecsCount": 12,
"Availability": 0.280093,
"Ident": "21e3d2b90978"
},
{
"Group": -1,
"Version": "09",
"Task": 0,
"Validator": 0,
"Executor": 1,
"TelemetryChunks": 0,
"ExecsCount": 0,
"Availability": 86.111111,
"Ident": "db71df911ec3"
},
{
"Group": -1,
"Version": "09",
"Task": 0,
"Validator": 0,
"Executor": 1,
"TelemetryChunks": 0,
"ExecsCount": 0,
"Availability": 86.109954,
"Ident": "6b19c0defd4c"
},
{
"Group": -1,
"Version": "09",
"Task": 0,
"Validator": 0,
"Executor": 1,
"TelemetryChunks": 0,
"ExecsCount": 0,
"Availability": 86.111111,
"Ident": "e469e8ad41f8"
},
{
"Group": -1,
"Version": "09",
"Task": 0,
"Validator": 0,
"Executor": 1,
"TelemetryChunks": 0,
"ExecsCount": 2,
"Availability": 86.109954,
"Ident": "4cbde0ae7db4"
},
{
"Group": -1,
"Version": "09",
"Task": 0,
"Validator": 0,
"Executor": 1,
"TelemetryChunks": 0,
"ExecsCount": 0,
"Availability": 86.111111,
"Ident": "cc43fddac1b0"
},
{
"Group": -1,
"Version": "09",
"Task": 0,
"Validator": 0,
"Executor": 1,
"TelemetryChunks": 0,
"ExecsCount": 0,
"Availability": 86.104167,
"Ident": "910ba68103f6"
},
{
"Group": -1,
"Version": "09",
"Task": 0,
"Validator": 0,
"Executor": 1,
"TelemetryChunks": 0,
"ExecsCount": 1,
"Availability": 86.111111,
"Ident": "17027d759e17"
},
{
"Group": -1,
"Version": "09",
"Task": 0,
"Validator": 0,
"Executor": 1,
"TelemetryChunks": 0,
"ExecsCount": 0,
"Availability": 86.111111,
"Ident": "10011a951b27"
}
]
},
{
"Username": "GRIDSHELLCoreValidators1",
"Rank": 10,
"Created": 1664609779,
"LastSeen": 1722263196,
"Balance": 1,
"Good": 13,
"Bad": 87,
"UPF": 13,
"Totals": 354,
"Submits": 129988,
"TelemetryCount": 4,
"TelemetryMax": 10,
"TelemetrySize": 100000,
"UPFDetais":"0000100000000000010000000000000010010000000010000000001010000000000010100000000100100000010010000000","Retention": 172800,
"Validator": 1,
"Nodes": 2,
"Awards":[
{
"Category": 0,
"Medal": 3
},
{
"Category": 1,
"Medal": 1
},
{
"Category": 2,
"Medal": 1
},
{
"Category": 3,
"Medal": 0
}
],
"Telemetry":[
{
"Created": 1722262599,
"Modified": 1722262599,
"Size": "8391",
"Name": "GRIDSHELLCoreValidators1CURRENT"
},
{
"Created": 1722117758,
"Modified": 1722203701,
"Size": "14625",
"Name": "GRIDSHELLCoreValidators1STAT2024728"
},
{
"Created": 1722204302,
"Modified": 1722263200,
"Size": "10043",
"Name": "GRIDSHELLCoreValidators1STAT2024729"
},
{
"Created": 1722262599,
"Modified": 1722262599,
"Size": "2242",
"Name": "GRIDSHELLCoreValidators1TASKS"
}
],
"NodesList":[
{
"Group": -1,
"Version": "09",
"Task": 0,
"Validator": 1,
"Executor": 1,
"TelemetryChunks": 0,
"ExecsCount": 20,
"Availability": 4.144676,
"Ident": "0d2fd996bb4c"
},
{
"Group": -1,
"Version": "09",
"Task": 0,
"Validator": 1,
"Executor": 1,
"TelemetryChunks": 0,
"ExecsCount": 15,
"Availability": 4.144676,
"Ident": "761eb6b6a1be"
}
]
},
{
"Username": "trialestesalamosaurustianzhenosaurus",
"Rank": 0,
"Created": 1708705684,
"LastSeen": 1722263199,
"Balance": 19735,
"Good": 100,
"Bad": 0,
"UPF": 100,
"Totals": 17588,
"Submits": 4094,
"TelemetryCount": 1,
"TelemetryMax": 5,
"TelemetrySize": 10000,
"UPFDetais":"1111111111111111111111111111111111111111111111111111111111111111111111111111111111111111111111111111","Retention": 86400,
"Validator": 0,
"Nodes": 7,
"Awards":[
{
"Category": 0,
"Medal": 1
},
{
"Category": 1,
"Medal": 2
},
{
"Category": 2,
"Medal": 1
},
{
"Category": 3,
"Medal": 1
}
],
"Telemetry":[
{
"Created": 1722192840,
"Modified": 1722261798,
"Size": "916",
"Name": "trialestesalamosaurustianzhenosaurusWATERMELON"
}
],
"NodesList":[
{
"Group": 3,
"Version": "09",
"Task": 0,
"Validator": 0,
"Executor": 1,
"TelemetryChunks": 0,
"ExecsCount": 188,
"Availability": 100.000000,
"Ident": "73c27bda8c67"
},
{
"Group": 3,
"Version": "09",
"Task": 0,
"Validator": 0,
"Executor": 1,
"TelemetryChunks": 0,
"ExecsCount": 116,
"Availability": 100.000000,
"Ident": "9122cc562c28"
},
{
"Group": 3,
"Version": "09",
"Task": 0,
"Validator": 0,
"Executor": 1,
"TelemetryChunks": 0,
"ExecsCount": 96,
"Availability": 100.000000,
"Ident": "637d6f57b53f"
},
{
"Group": 3,
"Version": "09",
"Task": 0,
"Validator": 0,
"Executor": 1,
"TelemetryChunks": 1,
"ExecsCount": 83,
"Availability": 100.000000,
"Ident": "cd0acda0224a"
},
{
"Group": 3,
"Version": "09",
"Task": 0,
"Validator": 0,
"Executor": 1,
"TelemetryChunks": 0,
"ExecsCount": 58,
"Availability": 100.000000,
"Ident": "2f496fce1559"
},
{
"Group": 3,
"Version": "09",
"Task": 0,
"Validator": 0,
"Executor": 1,
"TelemetryChunks": 0,
"ExecsCount": 4,
"Availability": 90.211806,
"Ident": "4b63ab6a7b39"
},
{
"Group": -1,
"Version": "09",
"Task": 0,
"Validator": 0,
"Executor": 1,
"TelemetryChunks": 0,
"ExecsCount": 2,
"Availability": 4.144676,
"Ident": "aff95a8f34ee"
}
]
},
{
"Username": "JadeChartreuseDromiceiomimus",
"Rank": 100,
"Created": 1668685680,
"LastSeen": 1722263191,
"Balance": 73808,
"Good": 100,
"Bad": 0,
"UPF": 100,
"Totals": 701704,
"Submits": 369873,
"TelemetryCount": 0,
"TelemetryMax": 1001,
"TelemetrySize": 1500000,
"UPFDetais":"1111111111111111111111111111111111111111111111111111111111111111111111111111111111111111111111111111","Retention": 604800,
"Validator": 0,
"Nodes": 1,
"Awards":[
{
"Category": 0,
"Medal": 3
},
{
"Category": 1,
"Medal": 3
},
{
"Category": 2,
"Medal": 1
},
{
"Category": 3,
"Medal": 2
}
],
"Telemetry":[
],
"NodesList":[
{
"Group": -1,
"Version": "09",
"Task": 0,
"Validator": 0,
"Executor": 1,
"TelemetryChunks": 0,
"ExecsCount": 2,
"Availability": 1.239583,
"Ident": "fc9db527bc6c"
}
]
}
]
}